Metadata-Version: 2.1
Name: fbchat-asyncio-kvgx12
Version: 0.6.24
Summary: Facebook Messenger for Python.
Author-email: kvgx12 <szczepan7700@gmail.com>
Requires-Python: >=3.9
Classifier: Development Status :: 3 - Alpha
Classifier: License :: OSI Approved :: BSD License
Classifier: Operating System :: OS Independent
Classifier: Programming Language :: Python :: 3
Classifier: Programming Language :: Python :: 3 :: Only
Classifier: Programming Language :: Python :: 3.9
Classifier: Programming Language :: Python :: 3.10
Classifier: Programming Language :: Python :: Implementation :: CPython
Classifier: Programming Language :: Python :: Implementation :: PyPy
Classifier: Topic :: Communications :: Chat
Classifier: Topic :: Internet :: WWW/HTTP
Classifier: Topic :: Software Development :: Libraries :: Python Modules
Requires-Dist: attrs>=19.1
Requires-Dist: beautifulsoup4~=4.0
Requires-Dist: aiohttp
Requires-Dist: yarl
Requires-Dist: paho-mqtt~=1.5
Requires-Dist: sphinx ; extra == "doc"
Requires-Dist: black ; extra == "lint"
Requires-Dist: pyright ; extra == "lint"
Requires-Dist: aiohttp-socks ; extra == "proxy"
Requires-Dist: pysocks ; extra == "proxy"
Requires-Dist: pytest>=4.3,<6.0 ; extra == "test"
Project-URL: Bug Tracker, https://github.com/kugo12/fbchat-asyncio/issues
Project-URL: Homepage, https://github.com/kugo12/fbchat-asyncio
Provides-Extra: doc
Provides-Extra: lint
Provides-Extra: proxy
Provides-Extra: test
